api_analytics/__init__.py
api_analytics/core.py
api_analytics/django.py
api_analytics/fastapi.py
api_analytics/flask.py
api_analytics/tornado.py
api_analytics-1.2.7.dist-info/licenses/LICENSE
api_analytics-1.2.7.dist-info/METADATA
api_analytics-1.2.7.dist-info/WHEEL
api_analytics-1.2.7.dist-info/top_level.txt
api_analytics-1.2.7.dist-info/RECORD
