Metadata-Version: 2.4
Name: api-analytics
Version: 1.2.7
Summary: Monitoring and analytics for Python API frameworks.
Author-email: Tom Draper <tomjdraper1@gmail.com>
License: MIT License
Project-URL: repository, https://github.com/tom-draper/api-analytics
Keywords: analytics,api,dashboard,django,fastapi,flask,tornado,middleware
Classifier: License :: OSI Approved :: MIT License
Classifier: Programming Language :: Python
Classifier: Programming Language :: Python :: 3
Requires-Python: >=3.6
License-File: LICENSE
Requires-Dist: requests
Provides-Extra: build
Requires-Dist: build; extra == "build"
Requires-Dist: twine; extra == "build"
Provides-Extra: dev
Requires-Dist: pytest; extra == "dev"
Provides-Extra: django
Requires-Dist: Django; extra == "django"
Provides-Extra: fastapi
Requires-Dist: fastapi; extra == "fastapi"
Provides-Extra: flask
Requires-Dist: Flask; extra == "flask"
Provides-Extra: tornado
Requires-Dist: tornado; extra == "tornado"
Dynamic: license-file
